setup.py
jikan/__init__.py
jikan/main.py
jikan/mnemonic.py
jikan.egg-info/PKG-INFO
jikan.egg-info/SOURCES.txt
jikan.egg-info/dependency_links.txt
jikan.egg-info/requires.txt
jikan.egg-info/top_level.txt
jikan/data/Heisigs_RTK_6th.json
jikan/data/mnemonics.txt
jikan/data/substitutions/kc_e2bfb0e4b8a8e4b8bf.svg
jikan/data/substitutions/kc_e2bfb0e4b8bfe4b880.svg
jikan/data/substitutions/kc_e2bfb0e696b9e2bfb0e4b8bfe4b880.svg
jikan/data/substitutions/kc_e2bfb0e69c88e2ba89.svg
jikan/data/substitutions/kc_e2bfb1e2ba8de58696.svg
jikan/data/substitutions/kc_e2bfb1e2ba95e6b0ba.svg
jikan/data/substitutions/kc_e2bfb1e2baa4e58696.svg
jikan/data/substitutions/kc_e2bfb1e2bc81e2bc83.svg
jikan/data/substitutions/kc_e2bfb1e4b880e58bbf.svg
jikan/data/substitutions/kc_e2bfb1e4b880e58eb6.svg
jikan/data/substitutions/kc_e2bfb1e4baa0e58eb6.svg
jikan/data/substitutions/kc_e2bfb1e58696e5b7be.svg
jikan/data/substitutions/kc_e2bfb1e58d81e697a9.svg
jikan/data/substitutions/kc_e2bfb1e59381e69ca8.svg
jikan/data/substitutions/kc_e2bfb1e59c9fe58fa3.svg
jikan/data/substitutions/kc_e2bfb1e697a5e58c82.svg
jikan/data/substitutions/kc_e2bfb1e7ab8be2bfb5e58682e58fa4.svg
jikan/data/substitutions/kc_e2bfb1e7ab8be58fa3.svg
jikan/data/substitutions/kc_e2bfb1e7bebde99ab9.svg
jikan/data/substitutions/kc_e2bfb1e889b9e4b880.svg
jikan/data/substitutions/kc_e2bfb1e889b9e6b0b5.svg
jikan/data/substitutions/kc_e2bfb1e889b9e99abb.svg
jikan/data/substitutions/kc_e2bfb3e2ba95e58696e58f88.svg
jikan/data/substitutions/kc_e2bfb3e2bfb0e4b8bfe4b880e697a5e5a482.svg
jikan/data/substitutions/kc_e2bfb3e4b880e58d9ce4baba.svg
jikan/data/substitutions/kc_e2bfb8e58d88e99ab9.svg
jikan/data/substitutions/kc_e2bfbae4b99ae7b1b3.svg
jikan/data/substitutions/kc_e2bfbbe2ba95e4ba85.svg
jikan/data/substitutions/kc_e2bfbbe4b880e4b8bf.svg
jikan/data/substitutions/kc_e2bfbbe4b880e4babb.svg
jikan/data/substitutions/kc_e2bfbbe4babbe3818f.svg
jikan/data/substitutions/kc_e2bfbbe59c9fe68888.svg
jikan/data/substitutions/kc_e2bfbbe794b0e4b99a.svg
jikan/data/substitutions/kc_e2bfbbe7be8ae4b8bf.svg
jikan/data/substitutions/kc_e4b88e2de4b880.svg
jikan/data/substitutions/kc_e8a1a32de4baa0.svg
