Metadata-Version: 1.1
Name: jikan
Version: 0.2.18
Summary: Kanji learning anki deck generator
Home-page: https://hydra.ecd.space/jikan/jikan/
Author: jikan@cock.li
Author-email: UNKNOWN
License: LGPLv3
Platform: UNKNOWN
Classifier: Programming Language :: Python :: 3 :: Only
